poetry_plugin_appimage/__init__.py
poetry_plugin_appimage/plugin.py
poetry_plugin_appimage/templates/CustomAppRun.sh.mako
poetry_plugin_appimage/templates/application.desktop.mako
poetry_plugin_appimage/templates/build_appimage.sh.mako
poetry_plugin_appimage/templates/icon.png
poetry_plugin_appimage/templates/linuxdeploy-plugin-compile.sh
poetry_plugin_appimage/templates/linuxdeploy-plugin-conda.sh
poetry_plugin_appimage/templates/linuxdeploy-plugin-copyapp.sh
poetry_plugin_appimage/templates/linuxdeploy-x86_64.AppImage
poetry_plugin_appimage-0.0.4.dist-info/METADATA
poetry_plugin_appimage-0.0.4.dist-info/WHEEL
poetry_plugin_appimage-0.0.4.dist-info/entry_points.txt
poetry_plugin_appimage-0.0.4.dist-info/RECORD
